[
    {
        "name":"Audio Description",
        "link":""
    },
    {
        "name":"Help Center",
        "link":""
    },
    {
        "name":"Gift Cards",
        "link":""
    },
    {
        "name":"Media Center",
        "link":""
    },
    {
        "name":"Investor Relations",
        "link":""
    },
    {
        "name":"Jobs",
        "link":""
    },
    {
        "name":"Terms of Use",
        "link":""
    },
    {
        "name":"Privacy",
        "link":""
    },
    {
        "name":"Legal Notices",
        "link":""
    },
    {
        "name":"Cookie Preferences",
        "link":""
    },
    {
        "name":"Cooperate Information",
        "link":""
    },
    {
        "name":"Contact Us",
        "link":""
    }
]